{
"id": "gen9vgc2023regulationc-1849847826",
"p1": {
"playerName": "Eldegoss32",
"fullTeam": [
{
"species": "Haxorus",
"nickname": "",
"item": "",
"ability": "",
"teraType": "",
"moves": []
},
{
"species": "Talonflame",
"nickname": "Talonflame",
"item": "",
"ability": "",
"teraType": "",
"moves": []
},
{
"species": "Flutter Mane",
"nickname": "Flutter Mane",
"item": "",
"ability": "",
"teraType": "",
"moves": ["Dazzling Gleam"]
},
{
"species": "Kingambit",
"nickname": "",
"item": "",
"ability": "",
"teraType": "",
"moves": []
},
{
"species": "Great Tusk",
"nickname": "Great Tusk",
"item": "",
"ability": "",
"teraType": "Ground",
"moves": ["Protect", "Earthquake"]
},
{
"species": "Palafin",
"nickname": "Palafin",
"item": "",
"ability": "",
"teraType": "",
"moves": ["Protect", "Taunt", "Wave Crash"]
}
],
"broughtTeam": ["Talonflame", "Flutter Mane", "Great Tusk", "Palafin"]
},
"p2": {
"playerName": "minionbanana57",
"fullTeam": [
{
"species": "Iron Hands",
"nickname": "Iron Hands",
"item": "",
"ability": "",
"teraType": "",
"moves": ["Wild Charge"]
},
{
"species": "Tyranitar",
"nickname": "",
"item": "",
"ability": "",
"teraType": "",
"moves": []
},
{
"species": "Garchomp",
"nickname": "Garchomp",
"item": "",
"ability": "",
"teraType": "",
"moves": ["Protect", "Earthquake"]
},
{
"species": "Gyarados",
"nickname": "Gyarados",
"item": "",
"ability": "Intimidate",
"teraType": "",
"moves": ["Thunder Wave", "Waterfall"]
},
{
"species": "Amoonguss",
"nickname": "",
"item": "",
"ability": "",
"teraType": "",
"moves": []
},
{
"species": "Flutter Mane",
"nickname": "Flutter Mane",
"item": "",
"ability": "",
"teraType": "Fairy",
"moves": ["Dazzling Gleam"]
}
],
"broughtTeam": ["Iron Hands", "Garchomp", "Gyarados", "Flutter Mane"]
},
"outcome": 0
}