{
"id": "gen9vgc2023regulationc-1852437219",
"p1": {
"playerName": "Steakman5",
"fullTeam": [
{
"species": "Hawlucha",
"nickname": "Hawlucha",
"item": "Psychic Seed",
"ability": "",
"teraType": "",
"moves": ["Acrobatics"]
},
{
"species": "Indeedee",
"nickname": "Indeedee",
"item": "Iapapa Berry",
"ability": "Psychic Surge",
"teraType": "",
"moves": ["Follow Me"]
},
{
"species": "Flutter Mane",
"nickname": "Flutter Mane",
"item": "Booster Energy",
"ability": "Protosynthesis",
"teraType": "",
"moves": ["Dazzling Gleam"]
},
{
"species": "Ting-Lu",
"nickname": "Ting-Lu",
"item": "",
"ability": "Vessel of Ruin",
"teraType": "",
"moves": []
},
{
"species": "Armarouge",
"nickname": "",
"item": "",
"ability": "",
"teraType": "",
"moves": []
},
{
"species": "Chien-Pao",
"nickname": "",
"item": "",
"ability": "",
"teraType": "",
"moves": []
}
],
"broughtTeam": ["Hawlucha", "Indeedee", "Flutter Mane", "Ting-Lu"]
},
"p2": {
"playerName": "anshar_training",
"fullTeam": [
{
"species": "Palafin",
"nickname": "",
"item": "",
"ability": "",
"teraType": "",
"moves": []
},
{
"species": "Flutter Mane",
"nickname": "Cornelia",
"item": "",
"ability": "",
"teraType": "Fairy",
"moves": ["Dazzling Gleam"]
},
{
"species": "Arcanine",
"nickname": "",
"item": "",
"ability": "",
"teraType": "",
"moves": []
},
{
"species": "Amoonguss",
"nickname": "Susy",
"item": "Sitrus Berry",
"ability": "",
"teraType": "",
"moves": ["Rage Powder"]
},
{
"species": "Ting-Lu",
"nickname": "Good Soup",
"item": "",
"ability": "Vessel of Ruin",
"teraType": "",
"moves": ["Heavy Slam"]
},
{
"species": "Roaring Moon",
"nickname": "",
"item": "",
"ability": "",
"teraType": "",
"moves": []
}
],
"broughtTeam": ["Flutter Mane", "Amoonguss", "Ting-Lu"]
},
"outcome": 0
}